tqdm/__init__.py
tqdm/__main__.py
tqdm/_dist_ver.py
tqdm/_main.py
tqdm/_monitor.py
tqdm/_tqdm.py
tqdm/_tqdm_gui.py
tqdm/_tqdm_notebook.py
tqdm/_tqdm_pandas.py
tqdm/_utils.py
tqdm/asyncio.py
tqdm/auto.py
tqdm/autonotebook.py
tqdm/cli.py
tqdm/completion.sh
tqdm/dask.py
tqdm/gui.py
tqdm/keras.py
tqdm/notebook.py
tqdm/rich.py
tqdm/std.py
tqdm/tk.py
tqdm/tqdm.1
tqdm/utils.py
tqdm/version.py
tqdm/contrib/__init__.py
tqdm/contrib/bells.py
tqdm/contrib/concurrent.py
tqdm/contrib/discord.py
tqdm/contrib/itertools.py
tqdm/contrib/logging.py
tqdm/contrib/slack.py
tqdm/contrib/telegram.py
tqdm/contrib/utils_worker.py
vscode_tqdm-4.66.2.dist-info/LICENCE
vscode_tqdm-4.66.2.dist-info/METADATA
vscode_tqdm-4.66.2.dist-info/WHEEL
vscode_tqdm-4.66.2.dist-info/entry_points.txt
vscode_tqdm-4.66.2.dist-info/top_level.txt
vscode_tqdm-4.66.2.dist-info/RECORD
